Workbook
Name Aporte: Planilha1!$D$17
Name patrimonio: Planilha1!$D$20
Name Qtd_anos: Planilha1!$D$18
Name Rendimento_carteira: Planilha1!$D$13
Name salario: Planilha1!$D$12
Name sugestao_investimento: Planilha1!$D$14
Name Taxa_mensal: Planilha1!$D$19

Sheet Planilha1
B11: CONFIGURAÇÕES
B12: Salario | D12: 2000
B13: Rendimento Carteira | D13: 0.006
B14: Segestão de investimento (30% ) | D14: =D12*30% -> 600
B16: INVESTIMENTO MENSAL
B17: Quanto investir por mês ? | D17: 200
B18: Por quantos anos ? | D18: 5
B19: Taxa de Rendimento Mensal ? | D19: 0.01079
B20: Patrimonio Acumulado ? | D20: =FV(D19,D18*12,D17*-1) -> 16755.383
B21: Dividendos mensais ? | D21: =D20*1% -> 167.55383
B23: Cenários | D23: Dividendo
A24: 2 | B24: Quanto em 2 Anos ? | C24: =FV($D$19,A24*12,$D$17*-1) -> 5445.5255 | D24: =C24*$D$13 -> 32.673153
A25: 5 | B25: Quanto em 5 Anos ? | C25: =FV($D$19,A25*12,$D$17*-1) -> 16755.383 | D25: =C25*$D$13 -> 100.5323
A26: 10 | B26: Quanto em 10 Anos ? | C26: =FV($D$19,A26*12,$D$17*-1) -> 48656.843 | D26: =C26*$D$13 -> 291.94106
A27: 20 | B27: Quanto em 20 Anos ? | C27: =FV($D$19,A27*12,$D$17*-1) -> 225039.68 | D27: =C27*$D$13 -> 1350.2381
A28: 30 | B28: Quanto em 30 Anos ? | C28: =FV($D$19,A28*12,$D$17*-1) -> 864433.93 | D28: =C28*$D$13 -> 5186.6036
B32: PERFIL | C32: Moderado
B33: VALOR A SER INVESTIDO POR MÊS | C33: =Aporte -> 200
B35: TIPO DE FII | C35: Percentual Sugerido | D35: Valores
B36: PAPEL | C36: =VLOOKUP($C$32&"-"&B36,Planilha2!$A:$D,4,) -> 0.32 | D36: =C36*$C$33 -> 64
B37: TIJOLO | C37: =VLOOKUP($C$32&"-"&B37,Planilha2!$A:$D,4,) -> 0.4 | D37: =C37*$C$33 -> 80
B38: HIBRIDOS | C38: =VLOOKUP($C$32&"-"&B38,Planilha2!$A:$D,4,) -> 0.08 | D38: =C38*$C$33 -> 16
B39: FOF'S | C39: =VLOOKUP($C$32&"-"&B39,Planilha2!$A:$D,4,) -> 0.1 | D39: =C39*$C$33 -> 20
B40: DESENVOLVIMENTO | C40: =VLOOKUP($C$32&"-"&B40,Planilha2!$A:$D,4,) -> 0.1 | D40: =C40*$C$33 -> 20
B41: HOTELARIAS | C41: =VLOOKUP($C$32&"-"&B41,Planilha2!$A:$D,4,) -> 0.1 | D41: =C41*$C$33 -> 20
D42: =SUM(D36:D41) -> 220

Sheet Planilha2
A2: CHAVE | B2: PERFIL | C2: TIPO DE FII | D2: %
A3: =B3&"-"&C3 -> Conservador-PAPEL | B3: Conservador | C3: PAPEL | D3: 0.3
A4: =B4&"-"&C4 -> Conservador-TIJOLO | B4: Conservador | C4: TIJOLO | D4: 0.5
A5: =B5&"-"&C5 -> Conservador-HIBRIDOS | B5: Conservador | C5: HIBRIDOS | D5: 0.1
A6: =B6&"-"&C6 -> Conservador-FOF'S | B6: Conservador | C6: FOF'S | D6: 0.1
A7: =B7&"-"&C7 -> Conservador-DESENVOLVIMENTO | B7: Conservador | C7: DESENVOLVIMENTO | D7: 0
A8: =B8&"-"&C8 -> Conservador-HOTELARIAS | B8: Conservador | C8: HOTELARIAS | D8: 0
A9: =B9&"-"&C9 -> Moderado-PAPEL | B9: Moderado | C9: PAPEL | D9: 0.32
A10: =B10&"-"&C10 -> Moderado-TIJOLO | B10: Moderado | C10: TIJOLO | D10: 0.4
A11: =B11&"-"&C11 -> Moderado-HIBRIDOS | B11: Moderado | C11: HIBRIDOS | D11: 0.08
A12: =B12&"-"&C12 -> Moderado-FOF'S | B12: Moderado | C12: FOF'S | D12: 0.1
A13: =B13&"-"&C13 -> Moderado-DESENVOLVIMENTO | B13: Moderado | C13: DESENVOLVIMENTO | D13: 0.1
A14: =B14&"-"&C14 -> Moderado-HOTELARIAS | B14: Moderado | C14: HOTELARIAS | D14: 0.1
... A20: =B20&"-"&C20 -> Agressivo-HOTELARIAS | B20: Agressivo | C20: HOTELARIAS | D20: 0.1
